aamrd/__init__.py
aamrd/hpc.py
aamrd/lava.py
aamrd/slurm.py
aamrd-22.4.dist-info/License.agpl
aamrd-22.4.dist-info/METADATA
aamrd-22.4.dist-info/WHEEL
aamrd-22.4.dist-info/top_level.txt
aamrd-22.4.dist-info/RECORD
